pymergevcd/__init__.py
pymergevcd/cli.py
pymergevcd/io_manager.py
pymergevcd/io_manager_interfaces.py
pymergevcd/merge_engine.py
pymergevcd/vcd_reader.py
pymergevcd/vcd_writer.py
pymergevcd-0.6.1.dist-info/LICENSE.txt
pymergevcd-0.6.1.dist-info/METADATA
pymergevcd-0.6.1.dist-info/WHEEL
pymergevcd-0.6.1.dist-info/entry_points.txt
pymergevcd-0.6.1.dist-info/top_level.txt
pymergevcd-0.6.1.dist-info/RECORD
