Metadata-Version: 2.1
Name: pymergevcd
Version: 0.6.1
Summary: Merge various VCD files
Home-page: https://github.com/kown7/pymergevcd
Author: Kristoffer Nordström
License: MIT
Keywords: python
Platform: UNKNOWN
Classifier: Development Status :: 4 - Beta
Classifier: Intended Audience :: Developers
Classifier: License :: OSI Approved :: MIT License
Classifier: Programming Language :: Python
Classifier: Programming Language :: Python :: 3
Classifier: Programming Language :: Python :: 3 :: Only
Classifier: Programming Language :: Python :: 3.6
Classifier: Programming Language :: Python :: 3.7
Classifier: Programming Language :: Python :: 3.8
Requires-Python: >=3.6
Requires-Dist: colorama (==0.4.3)
Requires-Dist: exitstatus (==1.4.0)
Requires-Dist: pyvcd (==0.2.1)
